Workbook
Name aporte: Simulador!$D$16
Name patrimonio: Simulador!$D$19
Name qtde_anos: Simulador!$D$17
Name rendimento_carteira: Simulador!$D$12
Name salario: Simulador!$D$11
Name sugestao_investimento: Simulador!$D$13
Name taxa_mensal: Simulador!$D$18

Sheet Simulador
B10: CONFIGURAÇÕES
B11: Salário | D11: 2000
B12: Rendimento Carteira | D12: 0.006
B13: Sugestão de Investimento (30%) | D13: =salario*30% -> 600
B15: INVESTIMENTO MENSAL
B16: Quanto Investir por Mês ? | D16: 200
B17: Por Quantos Anos ? | D17: 5
B18: Taxa de Rendimento Mensal ? | D18: 0.01079
B19: Patrimônio Acumulado ? | D19: =FV(taxa_mensal,qtde_anos*12,-aporte) -> 16755.383
B20: Dividendos Mensais ? | D20: =patrimonio*rendimento_carteira -> 100.5323
B22: CENÁRIOS | D22: Dividendos
A23: 2 | B23: Quanto em 2 anos? | C23: =FV(taxa_mensal,$A23*12,-aporte) -> 5445.5255 | D23: =C23*rendimento_carteira -> 32.673153
A24: 5 | B24: Quanto em 5 anos? | C24: =FV(taxa_mensal,$A24*12,-aporte) -> 16755.383 | D24: =C24*rendimento_carteira -> 100.5323
A25: 10 | B25: Quanto em 10 anos? | C25: =FV(taxa_mensal,$A25*12,-aporte) -> 48656.843 | D25: =C25*rendimento_carteira -> 291.94106
A26: 20 | B26: Quanto em 20 anos? | C26: =FV(taxa_mensal,$A26*12,-aporte) -> 225039.68 | D26: =C26*rendimento_carteira -> 1350.2381
A27: 30 | B27: Quanto em 30 anos? | C27: =FV(taxa_mensal,$A27*12,-aporte) -> 864433.93 | D27: =C27*rendimento_carteira -> 5186.6036
B29: SELECIONE SEU PERFIL | C29: Agressivo
B30: VALOR A SER INVESTIDO POR MÊS | C30: =aporte -> 200
B32: TIPO DE FII | C32: Percentual Sugerido | D32: Valores
B33: PAPEL | C33: =VLOOKUP($C$29&"-"&B33,'Taxas&Perfil'!A:D,4,FALSE) -> 0.5 | D33: =aporte*C33 -> 100
B34: TIJOLO | C34: =VLOOKUP($C$29&"-"&B34,'Taxas&Perfil'!A:D,4,FALSE) -> 0.1 | D34: =aporte*C34 -> 20
B35: HÍBRIDOS | C35: =VLOOKUP($C$29&"-"&B35,'Taxas&Perfil'!A:D,4,FALSE) -> 0.05 | D35: =aporte*C35 -> 10
B36: FOFs | C36: =VLOOKUP($C$29&"-"&B36,'Taxas&Perfil'!A:D,4,FALSE) -> 0.05 | D36: =aporte*C36 -> 10
B37: DESENVOLVIMENTO | C37: =VLOOKUP($C$29&"-"&B37,'Taxas&Perfil'!A:D,4,FALSE) -> 0.2 | D37: =aporte*C37 -> 40
B38: HOTELARIAS | C38: =VLOOKUP($C$29&"-"&B38,'Taxas&Perfil'!A:D,4,FALSE) -> 0.1 | D38: =aporte*C38 -> 20
C39: =SUM(C33:C38) -> 1 | D39: =SUM(D33:D38) -> 200

Sheet Taxas&Perfil
A2: CHAVE | B2: PERFIL | C2: TIPO DE FII | D2: %
A3: =B3&"-"&C3 -> Conservador-PAPEL | B3: Conservador | C3: PAPEL | D3: 0.3
A4: =B4&"-"&C4 -> Conservador-TIJOLO | B4: Conservador | C4: TIJOLO | D4: 0.5
A5: =B5&"-"&C5 -> Conservador-HÍBRIDOS | B5: Conservador | C5: HÍBRIDOS | D5: 0.1
A6: =B6&"-"&C6 -> Conservador-FOFs | B6: Conservador | C6: FOFs | D6: 0.1
A7: =B7&"-"&C7 -> Conservador-DESENVOLVIMENTO | B7: Conservador | C7: DESENVOLVIMENTO | D7: 0
A8: =B8&"-"&C8 -> Conservador-HOTELARIAS | B8: Conservador | C8: HOTELARIAS | D8: 0
A9: =B9&"-"&C9 -> Moderado-PAPEL | B9: Moderado | C9: PAPEL | D9: 0.32
A10: =B10&"-"&C10 -> Moderado-TIJOLO | B10: Moderado | C10: TIJOLO | D10: 0.35
A11: =B11&"-"&C11 -> Moderado-HÍBRIDOS | B11: Moderado | C11: HÍBRIDOS | D11: 0.08
A12: =B12&"-"&C12 -> Moderado-FOFs | B12: Moderado | C12: FOFs | D12: 0.05
A13: =B13&"-"&C13 -> Moderado-DESENVOLVIMENTO | B13: Moderado | C13: DESENVOLVIMENTO | D13: 0.1
A14: =B14&"-"&C14 -> Moderado-HOTELARIAS | B14: Moderado | C14: HOTELARIAS | D14: 0.1
... A20: =B20&"-"&C20 -> Agressivo-HOTELARIAS | B20: Agressivo | C20: HOTELARIAS | D20: 0.1
